fastapi_websocket_rpc/__init__.py
fastapi_websocket_rpc/connection_manager.py
fastapi_websocket_rpc/logger.py
fastapi_websocket_rpc/rpc_channel.py
fastapi_websocket_rpc/rpc_methods.py
fastapi_websocket_rpc/schemas.py
fastapi_websocket_rpc/simplewebsocket.py
fastapi_websocket_rpc/utils.py
fastapi_websocket_rpc/websocket_rpc_client.py
fastapi_websocket_rpc/websocket_rpc_endpoint.py
fastapi_websocket_rpc-0.1.29.dist-info/LICENSE
fastapi_websocket_rpc-0.1.29.dist-info/METADATA
fastapi_websocket_rpc-0.1.29.dist-info/WHEEL
fastapi_websocket_rpc-0.1.29.dist-info/top_level.txt
fastapi_websocket_rpc-0.1.29.dist-info/RECORD
