Metadata-Version: 2.1
Name: fastapi-websocket-rpc
Version: 0.1.29
Summary: A fast and durable bidirectional JSON RPC channel over Websockets and FastApi.
Home-page: https://github.com/permitio/fastapi_websocket_rpc
Author: Or Weis
Author-email: or@permit.io
Classifier: Programming Language :: Python :: 3
Classifier: License :: OSI Approved :: MIT License
Classifier: Operating System :: OS Independent
Classifier: Topic :: Internet :: WWW/HTTP :: HTTP Servers
Classifier: Topic :: Internet :: WWW/HTTP :: WSGI
Requires-Python: >=3.9
License-File: LICENSE
Requires-Dist: fastapi<1,>=0.109.1
Requires-Dist: packaging>=20.4
Requires-Dist: pydantic>=1.9.1
Requires-Dist: websockets>=10.3
Requires-Dist: tenacity>=8.0.1
Provides-Extra: websocket-client
Requires-Dist: websocket-client>=1.1.0; extra == "websocket-client"
